{
	"havez" : {
		"class" : "alchemist",
		"female" : false,
		"special" : false,
		"spellbook" : [ "precision" ],
		"texts" : {
			"name" : "Havez",
			"biography" : "Havez has an eye for anything that is quirky or odd. His personal effects are an unusual mix of items from all over Ashan - shadow silk cloths from Ygg-Chall, leatherwork from Irollan, jewels from the Dwarven mines, etc. His interest in the quaint and curious extends to his troops as well, he has for many decades studied the Gremlins and specializes in the upbringing and training of these lizard-like humanoids.",
			"specialty" : {
				"description" : "Increases the Speed of allied Gremlins, Master Gremlins, and Gremlin Mechanics by 1 and their Attack and Defense skills by 20% for every level (rounded up).",
				"tooltip" : "Creature Bonus: Gremlins",
				"name" : "Gremlins"
			}
		},

		"images" : {
			"small" : "heroes/tower/havez/portraitSmall.png",
			"large" : "heroes/tower/havez/portraitLarge.png",
			"specialtySmall" : "heroes/specialtySmall/Gremlins.png",
			"specialtyLarge" : "heroes/specialtyLarge/Gremlins.png"
		},

		"skills" : [
			{ "skill" : "artillery", "level": "basic" },
			{ "skill" : "ballistics", "level": "basic" }
		],
    
		"specialty" : {
			"creature" : "gremlin",
			"creatureLevel" : 1,
			"stepSize" : 20
		},
	
		"army" : [
			{
				"creature" : "gremlin",
				"min" : 30, "max" : 40
			},
			{
				"creature" : "ballista",
				"min" : 1, "max" : 1
			},
			{
				"creature" : "gremlin",
				"min" : 30, "max" : 40
			}
		]
	}
}